fastai2_extensions/__init__.py
fastai2_extensions/_nbdev.py
fastai2_extensions/core.py
fastai2_extensions/augment/__init__.py
fastai2_extensions/augment/albumentations.py
fastai2_extensions/augment/all.py
fastai2_extensions/augment/kornia.py
fastai2_extensions/augment/pil_filters.py
fastai2_extensions/inference/__init__.py
fastai2_extensions/inference/export.py
fastai2_extensions/interpret/__init__.py
fastai2_extensions/interpret/all.py
fastai2_extensions/interpret/compare.py
fastai2_extensions/interpret/gradcam.py
fastai2_extensions/interpret/interpret.py
fastai2_extensions-0.0.31.dist-info/LICENSE
fastai2_extensions-0.0.31.dist-info/METADATA
fastai2_extensions-0.0.31.dist-info/WHEEL
fastai2_extensions-0.0.31.dist-info/entry_points.txt
fastai2_extensions-0.0.31.dist-info/top_level.txt
fastai2_extensions-0.0.31.dist-info/RECORD
