Metadata-Version: 2.1
Name: fastai2-extensions
Version: 0.0.31
Summary: Computer vision focused utilities for the fastai2 libraries
Home-page: https://github.com/Synopsis/fastai2_extensions/tree/master/
Author: Rahul Somani
Author-email: rsomani95@gmail.com
License: Apache Software License 2.0
Keywords: fastai2,deep learning,visualisation,interpretation
Platform: UNKNOWN
Classifier: Development Status :: 2 - Pre-Alpha
Classifier: Intended Audience :: Developers
Classifier: License :: OSI Approved :: Apache Software License
Classifier: Natural Language :: English
Classifier: Programming Language :: Python :: 3.6
Classifier: Programming Language :: Python :: 3.7
Classifier: Programming Language :: Python :: 3.8
Requires-Python: >=3.6
